<?xml version="1.0" encoding="utf-8" ?><dwsync><file name="plano_de_conta_modelo.php" server="187.108.193.15/public_html/" local="3463765269" remote="318763443856661772" Dst="-1" /><file name="_ctrl.php" server="187.108.193.15/public_html/" local="3463765721" remote="318763443856662192" Dst="-1" /><file name="_ctrl_modelo_grupo.php" server="187.108.193.15/public_html/" local="3463676750" remote="318763443856659852" Dst="-1" /><file name="_functions.php" server="187.108.193.15/public_html/" local="3463765710" remote="318763443856662192" Dst="-1" /><file name="_functions_modelo_grupo.php" server="187.108.193.15/public_html/" local="3463674467" remote="318763443856659852" Dst="-1" /><file name="form.php" server="187.108.193.15/public_html/" local="3463765941" remote="318763443856662432" Dst="-1" /><file name="form_grupo.php" server="187.108.193.15/public_html/" local="3463681074" remote="318763443856659852" Dst="-1" /><file name="popula_select.php" server="187.108.193.15/public_html/" local="3463677009" remote="318763443856659852" Dst="-1" /></dwsync>