<?xml version="1.0" encoding="utf-8" ?><dwsync><file name="_ctrl.php" server="vkt.srv.br/public_html/" local="3438861364" remote="318763443831757872" Dst="-1" /><file name="_functions.php" server="vkt.srv.br/public_html/" local="3466181185" remote="318763443859077672" Dst="-1" /><file name="exportar_mensagem.php" server="vkt.srv.br/public_html/" local="3438766155" remote="318763443831662652" Dst="-1" /><file name="form.php" server="vkt.srv.br/public_html/" local="3438861344" remote="318763443831757812" Dst="-1" /><file name="importacao_email.php" server="vkt.srv.br/public_html/" local="3438946721" remote="318763443831843192" Dst="-1" /><file name="_functions.php" server="ftp.vkt.srv.br/public_html/" local="3438949348" remote="318763443831845832" Dst="-1" /><file name="emails.csv" server="vkt.srv.br/public_html/" local="3466182193" remote="318763443859078692" Dst="-1" /><file name="importacao_emails_marcelo.php" server="vkt.srv.br/public_html/" local="3466182259" remote="318763443859078752" Dst="-1" /></dwsync>