<?xml version="1.0" encoding="utf-8" ?><dwsync><file name="form_nova_avaliacao.php" server="vkt.srv.br/public_html/" local="3459419885" remote="318763443852316392" Dst="-1" /><file name="nota_aluno_avaliacao.php" server="vkt.srv.br/public_html/" local="3459448389" remote="318763443852344892" Dst="-1" /><file name="lista_avaliacao.php" server="vkt.srv.br/public_html/" local="3448451452" remote="318763443841362312" Dst="-1" /><file name="recebe_nota_aluno.php" server="vkt.srv.br/public_html/" local="3458238150" remote="318763443851134632" Dst="-1" /><file name="_ctrl.php" server="vkt.srv.br/public_html/" local="3459421033" remote="318763443852317532" Dst="-1" /><file name="_functions.php" server="vkt.srv.br/public_html/" local="3459447616" remote="318763443852344112" Dst="-1" /><file name="error_log" server="vkt.srv.br/public_html/" local="3447062712" remote="318763443839975592" Dst="-1" /><file name="lista_avaliacao_recuperacao.php" server="vkt.srv.br/public_html/" local="3447062712" remote="318763443839975592" Dst="-1" /><file name="nota_aluno_recuperacao.php" server="vkt.srv.br/public_html/" local="3447062712" remote="318763443839975592" Dst="-1" /><file name="professor_lancar_notas.php" server="vkt.srv.br/public_html/" local="3447062712" remote="318763443839975592" Dst="-1" /><file name="visualizar_notas_recuperacao.php" server="vkt.srv.br/public_html/" local="3447062712" remote="318763443839975592" Dst="-1" /><file name="nota_aluno_avaliacao.php" server="ftp.vkt.srv.br/public_html/" local="130185622480000000" remote="130185622200000000" Dst="-1" /><file name="form_nova_avaliacao.php" server="ftp.vkt.srv.br/public_html/" local="130190642350000000" remote="130190641800000000" Dst="-1" /><file name="form_relatorio_individual.php" server="vkt.srv.br/public_html/" local="3458754973" remote="318763443851651472" Dst="-1" /><file name="exportar_alunos.php" server="vkt.srv.br/public_html/" local="3459448601" remote="318763443852345132" Dst="-1" /><file name="form_importar.php" server="vkt.srv.br/public_html/" local="3459439443" remote="318763443852335952" Dst="-1" /><file name="form_exportar.php" server="vkt.srv.br/public_html/" local="3459448958" remote="318763443852345432" Dst="-1" /></dwsync>