<?xml version="1.0" encoding="utf-8" ?><dwsync><file name="1.png" server="ftp.vkt.srv.br/www/" local="3417113486" remote="318763443848457192" Dst="-1" /><file name="2.png" server="ftp.vkt.srv.br/www/" local="3417113486" remote="318763443848457192" Dst="-1" /><file name="3.png" server="ftp.vkt.srv.br/www/" local="3417113486" remote="318763443848457192" Dst="-1" /><file name="6.png" server="ftp.vkt.srv.br/www/" local="3417113486" remote="318763443848457192" Dst="-1" /><file name="b.png" server="ftp.vkt.srv.br/www/" local="3417113486" remote="318763443848457192" Dst="-1" /><file name="imgbrrazu.png" server="ftp.vkt.srv.br/www/" local="3417113486" remote="318763443848457192" Dst="-1" /><file name="imgbrrlrj.png" server="ftp.vkt.srv.br/www/" local="3417113486" remote="318763443848457192" Dst="-1" /><file name="imgpxlazu.png" server="ftp.vkt.srv.br/www/" local="3417113486" remote="318763443848457192" Dst="-1" /><file name="logo_empresa.png" server="ftp.vkt.srv.br/www/" local="3417113486" remote="318763443848457192" Dst="-1" /><file name="logobancoob.jpg" server="ftp.vkt.srv.br/www/" local="3417113486" remote="318763443848457192" Dst="-1" /><file name="logobanespa.jpg" server="ftp.vkt.srv.br/www/" local="3417113486" remote="318763443848457192" Dst="-1" /><file name="logobanestes.jpg" server="ftp.vkt.srv.br/www/" local="3417113486" remote="318763443848457192" Dst="-1" /><file name="logobb.jpg" server="ftp.vkt.srv.br/www/" local="3417113486" remote="318763443848457192" Dst="-1" /><file name="logobesc.jpg" server="ftp.vkt.srv.br/www/" local="3417113486" remote="318763443848457192" Dst="-1" /><file name="logobradesco.jpg" server="ftp.vkt.srv.br/www/" local="3417113486" remote="318763443848457192" Dst="-1" /><file name="logocaixa.jpg" server="ftp.vkt.srv.br/www/" local="3417113486" remote="318763443848457192" Dst="-1" /><file name="logohsbc.jpg" server="ftp.vkt.srv.br/www/" local="3417113486" remote="318763443848457192" Dst="-1" /><file name="logoitau.jpg" server="ftp.vkt.srv.br/www/" local="3417113486" remote="318763443848457192" Dst="-1" /><file name="logonossacaixa.jpg" server="ftp.vkt.srv.br/www/" local="3417113486" remote="318763443848457192" Dst="-1" /><file name="logoreal.jpg" server="ftp.vkt.srv.br/www/" local="3417113486" remote="318763443848457192" Dst="-1" /><file name="logosantander.jpg" server="ftp.vkt.srv.br/www/" local="3417113486" remote="318763443848457192" Dst="-1" /><file name="logosicredi.jpg" server="ftp.vkt.srv.br/www/" local="3417113486" remote="318763443848457192" Dst="-1" /><file name="logosudameris.jpg" server="ftp.vkt.srv.br/www/" local="3417113486" remote="318763443848457192" Dst="-1" /><file name="logounibanco.jpg" server="ftp.vkt.srv.br/www/" local="3417113486" remote="318763443848457192" Dst="-1" /><file name="p.png" server="ftp.vkt.srv.br/www/" local="3417113486" remote="318763443848457192" Dst="-1" /></dwsync>